pyserial_asyncio_fast-0.15.dist-info/licenses/CREDITS.rst
pyserial_asyncio_fast-0.15.dist-info/licenses/LICENSE.txt
serial_asyncio_fast/__init__.py
pyserial_asyncio_fast-0.15.dist-info/METADATA
pyserial_asyncio_fast-0.15.dist-info/WHEEL
pyserial_asyncio_fast-0.15.dist-info/top_level.txt
pyserial_asyncio_fast-0.15.dist-info/RECORD
