Metadata-Version: 2.4
Name: pyserial-asyncio-fast
Version: 0.15
Summary: Python Serial Port Extension - Asynchronous I/O support
Author: pySerial-team
License-Expression: BSD-3-Clause
Project-URL: Source code, https://github.com/home-assistant-libs/pyserial-asyncio-fast
Project-URL: Documentation, http://pyserial-asyncio.readthedocs.io
Classifier: Development Status :: 5 - Production/Stable
Classifier: Intended Audience :: Developers
Classifier: Intended Audience :: End Users/Desktop
Classifier: Natural Language :: English
Classifier: Operating System :: POSIX
Classifier: Operating System :: MacOS :: MacOS X
Classifier: Programming Language :: Python
Classifier: Programming Language :: Python :: 3
Classifier: Programming Language :: Python :: 3.9
Classifier: Programming Language :: Python :: 3.10
Classifier: Programming Language :: Python :: 3.11
Classifier: Programming Language :: Python :: 3.12
Classifier: Programming Language :: Python :: 3.13
Classifier: Topic :: Communications
Classifier: Topic :: Software Development :: Libraries
Classifier: Topic :: Software Development :: Libraries :: Python Modules
Classifier: Topic :: Terminals :: Serial
Requires-Python: >=3.9
License-File: LICENSE.txt
License-File: CREDITS.rst
Requires-Dist: pyserial
Dynamic: license-file
